<?xml version="1.0" encoding="UTF-8"?>
<con:soapui-project id="7151a7cd-d19a-477c-a9f9-7133c503523b" activeEnvironment="Default" name="calculator" resourceRoot="" soapui-version="5.2.1" abortOnError="false" runType="SEQUENTIAL" xmlns:con="http://eviware.com/soapui/config"><con:settings/><con:interface xsi:type="con:WsdlInterface" id="3d57dc40-ab42-4d0b-8b70-78cb97965a42" wsaVersion="NONE" name="CalculatorSoap" type="wsdl" bindingName="{http://tempuri.org/}CalculatorSoap" soapVersion="1_1" anonymous="optional" definition="http://www.dneonline.com/calculator.asmx?WSDL" xmlns:xsi="http://www.w3.org/2001/XMLSchema-instance"><con:settings/><con:definitionCache/><con:endpoints><con:endpoint>http://www.dneonline.com/calculator.asmx</con:endpoint></con:endpoints><con:operation id="68b7c578-56fa-4084-a908-c8b5f732f603" isOneWay="false" action="http://tempuri.org/Add" name="Add" bindingOperationName="Add" type="Request-Response" inputName="" receivesAttachments="false" sendsAttachments="false" anonymous="optional"><con:settings/><con:call id="15a7a6cc-9678-43e3-9aa0-60e9d19a0c49" name="Request 1"><con:settings/><con:encoding>UTF-8</con:encoding><con:endpoint>http://www.dneonline.com/calculator.asmx</con:endpoint><con:request><![CDATA[<soapenv:Envelope xmlns:soapenv="http://schemas.xmlsoap.org/soap/envelope/" xmlns:tem="http://tempuri.org/">
   <soapenv:Header/>
   <soapenv:Body>
      <tem:Add>
         <tem:intA>?</tem:intA>
         <tem:intB>?</tem:intB>
      </tem:Add>
   </soapenv:Body>
</soapenv:Envelope>]]></con:request><con:wsaConfig mustUnderstand="NONE" version="200508" action="http://tempuri.org/Add"/></con:call></con:operation><con:operation id="23c9e465-6e40-464a-b64e-cc54c35905d8" isOneWay="false" action="http://tempuri.org/Divide" name="Divide" bindingOperationName="Divide" type="Request-Response" inputName="" receivesAttachments="false" sendsAttachments="false" anonymous="optional"><con:settings/><con:call id="25d5ec45-a5c5-491f-8519-08c676ccf75a" name="Request 1"><con:settings/><con:encoding>UTF-8</con:encoding><con:endpoint>http://www.dneonline.com/calculator.asmx</con:endpoint><con:request><![CDATA[<soapenv:Envelope xmlns:soapenv="http://schemas.xmlsoap.org/soap/envelope/" xmlns:tem="http://tempuri.org/">
   <soapenv:Header/>
   <soapenv:Body>
      <tem:Divide>
         <tem:intA>?</tem:intA>
         <tem:intB>?</tem:intB>
      </tem:Divide>
   </soapenv:Body>
</soapenv:Envelope>]]></con:request><con:wsaConfig mustUnderstand="NONE" version="200508" action="http://tempuri.org/Divide"/></con:call></con:operation><con:operation id="73ed6bde-20ae-438b-941a-cc5574ccbb0a" isOneWay="false" action="http://tempuri.org/Multiply" name="Multiply" bindingOperationName="Multiply" type="Request-Response" inputName="" receivesAttachments="false" sendsAttachments="false" anonymous="optional"><con:settings/><con:call id="6b2098cd-28eb-474d-b1bc-667bd4d28c7d" name="Request 1"><con:settings/><con:encoding>UTF-8</con:encoding><con:endpoint>http://www.dneonline.com/calculator.asmx</con:endpoint><con:request><![CDATA[<soapenv:Envelope xmlns:soapenv="http://schemas.xmlsoap.org/soap/envelope/" xmlns:tem="http://tempuri.org/">
   <soapenv:Header/>
   <soapenv:Body>
      <tem:Multiply>
         <tem:intA>?</tem:intA>
         <tem:intB>?</tem:intB>
      </tem:Multiply>
   </soapenv:Body>
</soapenv:Envelope>]]></con:request><con:wsaConfig mustUnderstand="NONE" version="200508" action="http://tempuri.org/Multiply"/></con:call></con:operation><con:operation id="37837df3-5584-4bb9-85ab-30588e411f85" isOneWay="false" action="http://tempuri.org/Subtract" name="Subtract" bindingOperationName="Subtract" type="Request-Response" inputName="" receivesAttachments="false" sendsAttachments="false" anonymous="optional"><con:settings/><con:call id="ddc652a9-8717-422a-8c4b-c63f3a41c2d9" name="Request 1"><con:settings/><con:encoding>UTF-8</con:encoding><con:endpoint>http://www.dneonline.com/calculator.asmx</con:endpoint><con:request><![CDATA[<soapenv:Envelope xmlns:soapenv="http://schemas.xmlsoap.org/soap/envelope/" xmlns:tem="http://tempuri.org/">
   <soapenv:Header/>
   <soapenv:Body>
      <tem:Subtract>
         <tem:intA>?</tem:intA>
         <tem:intB>?</tem:intB>
      </tem:Subtract>
   </soapenv:Body>
</soapenv:Envelope>]]></con:request><con:wsaConfig mustUnderstand="NONE" version="200508" action="http://tempuri.org/Subtract"/></con:call></con:operation></con:interface><con:interface xsi:type="con:WsdlInterface" id="e42d72dd-7ae2-4708-ac4d-f9163892643d" wsaVersion="NONE" name="CalculatorSoap12" type="wsdl" bindingName="{http://tempuri.org/}CalculatorSoap12" soapVersion="1_2" anonymous="optional" definition="http://www.dneonline.com/calculator.asmx?WSDL" xmlns:xsi="http://www.w3.org/2001/XMLSchema-instance"><con:settings/><con:definitionCache type="TEXT" rootPart="http://www.dneonline.com/calculator.asmx?WSDL"><con:part><con:url>http://www.dneonline.com/calculator.asmx?WSDL</con:url><con:content><![CDATA[<wsdl:definitions targetNamespace="http://tempuri.org/" xmlns:soap="http://schemas.xmlsoap.org/wsdl/soap/" xmlns:tm="http://microsoft.com/wsdl/mime/textMatching/" xmlns:soapenc="http://schemas.xmlsoap.org/soap/encoding/" xmlns:mime="http://schemas.xmlsoap.org/wsdl/mime/" xmlns:tns="http://tempuri.org/" xmlns:s="http://www.w3.org/2001/XMLSchema" xmlns:soap12="http://schemas.xmlsoap.org/wsdl/soap12/" xmlns:http="http://schemas.xmlsoap.org/wsdl/http/" xmlns:wsdl="http://schemas.xmlsoap.org/wsdl/">
  <wsdl:types>
    <s:schema elementFormDefault="qualified" targetNamespace="http://tempuri.org/">
      <s:element name="Add">
        <s:complexType>
          <s:sequence>
            <s:element minOccurs="1" maxOccurs="1" name="intA" type="s:int"/>
            <s:element minOccurs="1" maxOccurs="1" name="intB" type="s:int"/>
          </s:sequence>
        </s:complexType>
      </s:element>
      <s:element name="AddResponse">
        <s:complexType>
          <s:sequence>
            <s:element minOccurs="1" maxOccurs="1" name="AddResult" type="s:int"/>
          </s:sequence>
        </s:complexType>
      </s:element>
      <s:element name="Subtract">
        <s:complexType>
          <s:sequence>
            <s:element minOccurs="1" maxOccurs="1" name="intA" type="s:int"/>
            <s:element minOccurs="1" maxOccurs="1" name="intB" type="s:int"/>
          </s:sequence>
        </s:complexType>
      </s:element>
      <s:element name="SubtractResponse">
        <s:complexType>
          <s:sequence>
            <s:element minOccurs="1" maxOccurs="1" name="SubtractResult" type="s:int"/>
          </s:sequence>
        </s:complexType>
      </s:element>
      <s:element name="Multiply">
        <s:complexType>
          <s:sequence>
            <s:element minOccurs="1" maxOccurs="1" name="intA" type="s:int"/>
            <s:element minOccurs="1" maxOccurs="1" name="intB" type="s:int"/>
          </s:sequence>
        </s:complexType>
      </s:element>
      <s:element name="MultiplyResponse">
        <s:complexType>
          <s:sequence>
            <s:element minOccurs="1" maxOccurs="1" name="MultiplyResult" type="s:int"/>
          </s:sequence>
        </s:complexType>
      </s:element>
      <s:element name="Divide">
        <s:complexType>
          <s:sequence>
            <s:element minOccurs="1" maxOccurs="1" name="intA" type="s:int"/>
            <s:element minOccurs="1" maxOccurs="1" name="intB" type="s:int"/>
          </s:sequence>
        </s:complexType>
      </s:element>
      <s:element name="DivideResponse">
        <s:complexType>
          <s:sequence>
            <s:element minOccurs="1" maxOccurs="1" name="DivideResult" type="s:int"/>
          </s:sequence>
        </s:complexType>
      </s:element>
    </s:schema>
  </wsdl:types>
  <wsdl:message name="AddSoapIn">
    <wsdl:part name="parameters" element="tns:Add"/>
  </wsdl:message>
  <wsdl:message name="AddSoapOut">
    <wsdl:part name="parameters" element="tns:AddResponse"/>
  </wsdl:message>
  <wsdl:message name="SubtractSoapIn">
    <wsdl:part name="parameters" element="tns:Subtract"/>
  </wsdl:message>
  <wsdl:message name="SubtractSoapOut">
    <wsdl:part name="parameters" element="tns:SubtractResponse"/>
  </wsdl:message>
  <wsdl:message name="MultiplySoapIn">
    <wsdl:part name="parameters" element="tns:Multiply"/>
  </wsdl:message>
  <wsdl:message name="MultiplySoapOut">
    <wsdl:part name="parameters" element="tns:MultiplyResponse"/>
  </wsdl:message>
  <wsdl:message name="DivideSoapIn">
    <wsdl:part name="parameters" element="tns:Divide"/>
  </wsdl:message>
  <wsdl:message name="DivideSoapOut">
    <wsdl:part name="parameters" element="tns:DivideResponse"/>
  </wsdl:message>
  <wsdl:portType name="CalculatorSoap">
    <wsdl:operation name="Add">
      <wsdl:documentation>Adds two integers. This is a test WebService. ©DNE Online</wsdl:documentation>
      <wsdl:input message="tns:AddSoapIn"/>
      <wsdl:output message="tns:AddSoapOut"/>
    </wsdl:operation>
    <wsdl:operation name="Subtract">
      <wsdl:input message="tns:SubtractSoapIn"/>
      <wsdl:output message="tns:SubtractSoapOut"/>
    </wsdl:operation>
    <wsdl:operation name="Multiply">
      <wsdl:input message="tns:MultiplySoapIn"/>
      <wsdl:output message="tns:MultiplySoapOut"/>
    </wsdl:operation>
    <wsdl:operation name="Divide">
      <wsdl:input message="tns:DivideSoapIn"/>
      <wsdl:output message="tns:DivideSoapOut"/>
    </wsdl:operation>
  </wsdl:portType>
  <wsdl:binding name="CalculatorSoap" type="tns:CalculatorSoap">
    <soap:binding transport="http://schemas.xmlsoap.org/soap/http"/>
    <wsdl:operation name="Add">
      <soap:operation soapAction="http://tempuri.org/Add" style="document"/>
      <wsdl:input>
        <soap:body use="literal"/>
      </wsdl:input>
      <wsdl:output>
        <soap:body use="literal"/>
      </wsdl:output>
    </wsdl:operation>
    <wsdl:operation name="Subtract">
      <soap:operation soapAction="http://tempuri.org/Subtract" style="document"/>
      <wsdl:input>
        <soap:body use="literal"/>
      </wsdl:input>
      <wsdl:output>
        <soap:body use="literal"/>
      </wsdl:output>
    </wsdl:operation>
    <wsdl:operation name="Multiply">
      <soap:operation soapAction="http://tempuri.org/Multiply" style="document"/>
      <wsdl:input>
        <soap:body use="literal"/>
      </wsdl:input>
      <wsdl:output>
        <soap:body use="literal"/>
      </wsdl:output>
    </wsdl:operation>
    <wsdl:operation name="Divide">
      <soap:operation soapAction="http://tempuri.org/Divide" style="document"/>
      <wsdl:input>
        <soap:body use="literal"/>
      </wsdl:input>
      <wsdl:output>
        <soap:body use="literal"/>
      </wsdl:output>
    </wsdl:operation>
  </wsdl:binding>
  <wsdl:binding name="CalculatorSoap12" type="tns:CalculatorSoap">
    <soap12:binding transport="http://schemas.xmlsoap.org/soap/http"/>
    <wsdl:operation name="Add">
      <soap12:operation soapAction="http://tempuri.org/Add" style="document"/>
      <wsdl:input>
        <soap12:body use="literal"/>
      </wsdl:input>
      <wsdl:output>
        <soap12:body use="literal"/>
      </wsdl:output>
    </wsdl:operation>
    <wsdl:operation name="Subtract">
      <soap12:operation soapAction="http://tempuri.org/Subtract" style="document"/>
      <wsdl:input>
        <soap12:body use="literal"/>
      </wsdl:input>
      <wsdl:output>
        <soap12:body use="literal"/>
      </wsdl:output>
    </wsdl:operation>
    <wsdl:operation name="Multiply">
      <soap12:operation soapAction="http://tempuri.org/Multiply" style="document"/>
      <wsdl:input>
        <soap12:body use="literal"/>
      </wsdl:input>
      <wsdl:output>
        <soap12:body use="literal"/>
      </wsdl:output>
    </wsdl:operation>
    <wsdl:operation name="Divide">
      <soap12:operation soapAction="http://tempuri.org/Divide" style="document"/>
      <wsdl:input>
        <soap12:body use="literal"/>
      </wsdl:input>
      <wsdl:output>
        <soap12:body use="literal"/>
      </wsdl:output>
    </wsdl:operation>
  </wsdl:binding>
  <wsdl:service name="Calculator">
    <wsdl:port name="CalculatorSoap" binding="tns:CalculatorSoap">
      <soap:address location="http://www.dneonline.com/calculator.asmx"/>
    </wsdl:port>
    <wsdl:port name="CalculatorSoap12" binding="tns:CalculatorSoap12">
      <soap12:address location="http://www.dneonline.com/calculator.asmx"/>
    </wsdl:port>
  </wsdl:service>
</wsdl:definitions>]]></con:content><con:type>http://schemas.xmlsoap.org/wsdl/</con:type></con:part></con:definitionCache><con:endpoints><con:endpoint>http://www.dneonline.com/calculator.asmx</con:endpoint></con:endpoints><con:operation id="5ea27da2-072b-4995-a96e-a968f19072d2" isOneWay="false" action="http://tempuri.org/Add" name="Add" bindingOperationName="Add" type="Request-Response" inputName="" receivesAttachments="false" sendsAttachments="false" anonymous="optional"><con:settings/><con:call id="c36d4085-4a98-478e-b807-2a26e8c96fe6" name="Request 1"><con:settings><con:setting id="com.eviware.soapui.impl.wsdl.WsdlRequest@request-headers">&lt;xml-fragment/></con:setting></con:settings><con:encoding>UTF-8</con:encoding><con:endpoint>http://www.dneonline.com/calculator.asmx</con:endpoint><con:request><![CDATA[<soap:Envelope xmlns:soap="http://www.w3.org/2003/05/soap-envelope" xmlns:tem="http://tempuri.org/">
   <soap:Header/>
   <soap:Body>
      <tem:Add>
         <tem:intA>1</tem:intA>
         <tem:intB>2</tem:intB>
      </tem:Add>
   </soap:Body>
</soap:Envelope>]]></con:request><con:credentials><con:authType>No Authorization</con:authType></con:credentials><con:jmsConfig JMSDeliveryMode="PERSISTENT"/><con:jmsPropertyConfig/><con:wsaConfig mustUnderstand="NONE" version="200508" action="http://tempuri.org/CalculatorSoap/AddRequest"/><con:wsrmConfig version="1.2"/></con:call></con:operation><con:operation id="43cf133c-325f-4fa6-b73f-534291c097f3" isOneWay="false" action="http://tempuri.org/Divide" name="Divide" bindingOperationName="Divide" type="Request-Response" inputName="" receivesAttachments="false" sendsAttachments="false" anonymous="optional"><con:settings/><con:call id="27e27084-01ca-4873-9802-9c57330f04f7" name="Request 1"><con:settings/><con:encoding>UTF-8</con:encoding><con:endpoint>http://www.dneonline.com/calculator.asmx</con:endpoint><con:request><![CDATA[<soap:Envelope xmlns:soap="http://www.w3.org/2003/05/soap-envelope" xmlns:tem="http://tempuri.org/">
   <soap:Header/>
   <soap:Body>
      <tem:Divide>
         <tem:intA>?</tem:intA>
         <tem:intB>?</tem:intB>
      </tem:Divide>
   </soap:Body>
</soap:Envelope>]]></con:request><con:wsaConfig mustUnderstand="NONE" version="200508" action="http://tempuri.org/CalculatorSoap/DivideRequest"/></con:call></con:operation><con:operation id="9e1adbe1-1a0a-402b-b727-d5ddb1d030a1" isOneWay="false" action="http://tempuri.org/Multiply" name="Multiply" bindingOperationName="Multiply" type="Request-Response" inputName="" receivesAttachments="false" sendsAttachments="false" anonymous="optional"><con:settings/><con:call id="3b00d296-029c-4412-ac4b-f908674a7d04" name="Request 1"><con:settings/><con:encoding>UTF-8</con:encoding><con:endpoint>http://www.dneonline.com/calculator.asmx</con:endpoint><con:request><![CDATA[<soap:Envelope xmlns:soap="http://www.w3.org/2003/05/soap-envelope" xmlns:tem="http://tempuri.org/">
   <soap:Header/>
   <soap:Body>
      <tem:Multiply>
         <tem:intA>?</tem:intA>
         <tem:intB>?</tem:intB>
      </tem:Multiply>
   </soap:Body>
</soap:Envelope>]]></con:request><con:wsaConfig mustUnderstand="NONE" version="200508" action="http://tempuri.org/CalculatorSoap/MultiplyRequest"/></con:call></con:operation><con:operation id="2fa31f20-907c-4b29-bc3e-53df1d4cbbbe" isOneWay="false" action="http://tempuri.org/Subtract" name="Subtract" bindingOperationName="Subtract" type="Request-Response" inputName="" receivesAttachments="false" sendsAttachments="false" anonymous="optional"><con:settings/><con:call id="dcc7a2aa-1420-420b-ab9d-85ed723f7517" name="Request 1"><con:settings/><con:encoding>UTF-8</con:encoding><con:endpoint>http://www.dneonline.com/calculator.asmx</con:endpoint><con:request><![CDATA[<soap:Envelope xmlns:soap="http://www.w3.org/2003/05/soap-envelope" xmlns:tem="http://tempuri.org/">
   <soap:Header/>
   <soap:Body>
      <tem:Subtract>
         <tem:intA>?</tem:intA>
         <tem:intB>?</tem:intB>
      </tem:Subtract>
   </soap:Body>
</soap:Envelope>]]></con:request><con:wsaConfig mustUnderstand="NONE" version="200508" action="http://tempuri.org/CalculatorSoap/SubtractRequest"/></con:call></con:operation></con:interface><con:testSuite id="7778abe1-7514-4338-bde7-24292adb472a" name="TestSuite 1"><con:settings/><con:runType>SEQUENTIAL</con:runType><con:testCase id="24493c93-2f58-493a-b883-9ac9214dba15" failOnError="true" failTestCaseOnErrors="true" keepSession="false" maxResults="0" name="DataDriven" searchProperties="true"><con:settings/><con:testStep type="groovy" name="Groovy Script" id="4ef81fd7-16fb-4919-92e9-1a4f77738b7e"><con:settings/><con:config><script>def groovyUtils = new com.eviware.soapui.support.GroovyUtils(context)

// Path to csv file
def filePath = "/Users/incognito/Downloads/webservice testing/soapui-scripts/testdata.csv";
context.fileReader = new BufferedReader(new FileReader(filePath));

def testCase = context.testCase;
def propertiesStep = testCase.getTestStepByName('StoreCsvValues');

rowsData = context.fileReader.readLines();
int rowsize = rowsData.size();


for(int i=0;i&lt;rowsize;i++)
{
	log.info 'Printing row ' +i+ ' values'
    	rowdata = rowsData[i]
    	String[] values = rowdata.split(";")
    	log.info values[0]
    	log.info values[1]

	propertiesStep.setPropertyValue('value1',values[0]);
	propertiesStep.setPropertyValue('value2',values[1]);

	testRunner.runTestStepByName('AddTestRequest');
}</script></con:config></con:testStep><con:testStep type="properties" name="StoreCsvValues" id="23fb8df2-2f8b-4e35-b742-9ab6403223f4"><con:settings/><con:config xsi:type="con:PropertiesStep" saveFirst="true" xmlns:xsi="http://www.w3.org/2001/XMLSchema-instance"><con:properties><con:property><con:name>value1</con:name><con:value>60</con:value></con:property><con:property><con:name>value2</con:name><con:value>70</con:value></con:property></con:properties></con:config></con:testStep><con:testStep type="request" id="ad98862f-c96f-46e8-ba01-8cea3c63efc0" name="AddTestRequest"><con:settings/><con:config xsi:type="con:RequestStep" xmlns:xsi="http://www.w3.org/2001/XMLSchema-instance"><con:interface>CalculatorSoap12</con:interface><con:operation>Add</con:operation><con:request name="AddTestRequest" outgoingWss="" incomingWss="" timeout="" sslKeystore="" useWsAddressing="false" useWsReliableMessaging="false" wssPasswordType="" id="3acf9a58-0ca8-4b04-85cc-9914527dccc5"><con:settings><con:setting id="com.eviware.soapui.impl.wsdl.WsdlRequest@request-headers">&lt;xml-fragment/></con:setting></con:settings><con:encoding>UTF-8</con:encoding><con:endpoint>http://www.dneonline.com/calculator.asmx</con:endpoint><con:request><![CDATA[<soap:Envelope xmlns:soap="http://www.w3.org/2003/05/soap-envelope" xmlns:tem="http://tempuri.org/">
   <soap:Header/>
   <soap:Body>
      <tem:Add>
         <tem:intA>${StoreCsvValues#value1}</tem:intA>
         <tem:intB>${StoreCsvValues#value2}</tem:intB>
      </tem:Add>
   </soap:Body>
</soap:Envelope>]]></con:request><con:assertion type="SOAP Response" id="e9e59775-392c-4816-a1a2-6a819d1fe505" name="SOAP Response"/><con:assertion type="GroovyScriptAssertion" id="5c8dc1ff-a880-4647-982d-236a41578981" name="Script Assertion"><con:configuration><scriptText>// context - An object that holds information about a validation in-progress, such as the cursor of the content to be validated., etc.
def groovyUtils = new com.eviware.soapui.support.GroovyUtils( context );

// request holder
def requestContent = messageExchange.getRequestContentAsXml();

// response holder
def responseContent = messageExchange.getResponseContentAsXml();

// Get input parameters from request xml
def reqholder = groovyUtils.getXmlHolder(requestContent);

// getNodeValue returns string, convert them into Int
def value1 = reqholder.getNodeValue('//tem:intA').toInteger();
def value2 = reqholder.getNodeValue('//tem:intB').toInteger();

log.info 'Input values :' + value1 + ' &amp; ' + value2;

// Get the output parameter from response content
def resholder = groovyUtils.getXmlHolder(responseContent);

// Important: Check response content, there is a namespace defined in 
// response but not used with nodes
resholder.namespaces["ns"] = "http://tempuri.org/"

// Get the response output in Integer 
def addResponseValue = resholder.getNodeValue('//ns:AddResult').toInteger();
log.info 'Response : ' + addResponseValue

// Assert that addition of input values equal to response output
assert (addResponseValue = value1 + value2);

</scriptText></con:configuration></con:assertion><con:credentials><con:authType>No Authorization</con:authType></con:credentials><con:jmsConfig JMSDeliveryMode="PERSISTENT"/><con:jmsPropertyConfig/><con:wsaConfig mustUnderstand="NONE" version="200508" action="http://tempuri.org/CalculatorSoap/AddRequest"/><con:wsrmConfig version="1.2"/></con:request></con:config></con:testStep><con:properties/></con:testCase><con:properties/></con:testSuite><con:properties/><con:wssContainer/><con:oAuth2ProfileContainer/><con:sensitiveInformation/></con:soapui-project>